sinapsis_f5_tts/__init__.py
sinapsis_f5_tts/helpers/__init__.py
sinapsis_f5_tts/helpers/tags.py
sinapsis_f5_tts/templates/__init__.py
sinapsis_f5_tts/templates/f5_tts_inference.py
sinapsis_f5_tts-0.1.10.dist-info/licenses/LICENSE
sinapsis_f5_tts-0.1.10.dist-info/METADATA
sinapsis_f5_tts-0.1.10.dist-info/WHEEL
sinapsis_f5_tts-0.1.10.dist-info/top_level.txt
sinapsis_f5_tts-0.1.10.dist-info/RECORD
