Metadata-Version: 2.4
Name: sinapsis-f5-tts
Version: 0.1.10
Summary: Text to speech using F5-TTS library
Author-email: SinapsisAI <dev@sinapsis.tech>
Project-URL: Homepage, https://sinapsis.tech
Project-URL: Documentation, https://docs.sinapsis.tech/docs/sinapsis-speech
Project-URL: Tutorials, https://docs.sinapsis.tech/tutorials
Project-URL: Repository, https://github.com/Sinapsis-AI/sinapsis-speech.git
Requires-Python: >=3.10
License-File: LICENSE
Requires-Dist: f5-tts>=1.0.3
Requires-Dist: sinapsis>=0.2.2
Requires-Dist: soundfile>=0.12.1
Provides-Extra: sinapsis-data-tools
Requires-Dist: sinapsis-data-readers>=0.1.0; extra == "sinapsis-data-tools"
Requires-Dist: sinapsis-data-writers>=0.1.0; extra == "sinapsis-data-tools"
Provides-Extra: all
Requires-Dist: sinapsis-f5-tts[sinapsis-data-tools]; extra == "all"
Dynamic: license-file
